maccarone/__init__.py
maccarone/openai.py
maccarone/preprocessor.py
maccarone/scripts/preprocess.py
maccarone/test/test_preprocessor.py
maccarone-0.1.9.dist-info/LICENSE
maccarone-0.1.9.dist-info/METADATA
maccarone-0.1.9.dist-info/WHEEL
maccarone-0.1.9.dist-info/entry_points.txt
maccarone-0.1.9.dist-info/top_level.txt
maccarone-0.1.9.dist-info/RECORD
