Metadata-Version: 2.1
Name: maccarone
Version: 0.1.9
Summary: Mix natural language into your Python code
Project-URL: Homepage, https://github.com/bsilverthorn/maccarone
Project-URL: Repository, https://github.com/bsilverthorn/maccarone
Requires-Python: >=3.8
License-File: LICENSE
Requires-Dist: openai
Requires-Dist: parsimonious
Provides-Extra: dev
Requires-Dist: pytest ; extra == 'dev'
Requires-Dist: pytest-asyncio ; extra == 'dev'
Requires-Dist: ipython ; extra == 'dev'
Requires-Dist: pip-tools ; extra == 'dev'
